Workbook

Sheet Lote I - Total 
A1: DATA DA ESCRITURA | B1: FRAÇÃO | C1: BLOCO | D1: PISO | E1: APART. | F1: nº | G1: ANOMALIAS | H1: EMPRESA | I1: ESTADO entre 01/07/2026 a 07/07/2026 | J1: DATA ENTRADA ANOMALIA | K1: ESTADO | L1: DATA DA VISTORIA | M1: AGENDAM. CORREÇÃO/ DATA ENCOMENDA | N1: DATA de CORREÇÃO_BAIXA | O1: CONTACTO / NOTAS | P1: NÃO INTERVENCIONADO ANTIGUIDADE (DIAS) | Q1: ENCOMENDADO ANTIGUIDADE (DIAS) | R1: EM OBRA ANTIGUIDADE (DIAS) | S1: CORREÇÃO NÃO ACEITE ANTIGUIDADE (DIAS) | T1: A VERIFICAR ANTIGUIDADE (DIAS) | U1: COLUNA 1 | V1: COLUNA 2 | W1: COLUNA 3 | X1: COLUNA 4 | Y1: COLUNA 5 | Z1: COLUNA 6 | AA1: COLUNA 7
A2: 45499 | B2: A | C2: A | D2: -1 | E2: a | F2: 1 | G2: Substituir réguas do piso | H2: AR | K2: REPARADO | L2: 45322 | N2: 45656 | O2: Solange calado - 91 4719646 | P2: =IF(K2="NÃO INTERVENCIONADO",TODAY()-J2,"") | Q2: =IF(K2="ENCOMENDADO",TODAY()-J2,"") | R2: =IF(K2="EM OBRA",TODAY()-J2,"") | S2: =IF(K2="CORREÇÃO NÃO ACEITE",TODAY()-J2,"") | T2: =IF(K2="A VERIFICAR",TODAY()-J2,"")
A3: 45499 | B3: A | C3: A | D3: -1 | E3: a | F3: 2 | G3: Bordas do armário com defeito | H3: AR | K3: REPARADO | L3: 45322 | N3: 45656 | O3: Solange calado - 91 4719646 | P3: =IF(K3="NÃO INTERVENCIONADO",TODAY()-J3,"") | Q3: =IF(K3="ENCOMENDADO",TODAY()-J3,"") | R3: =IF(K3="EM OBRA",TODAY()-J3,"") | S3: =IF(K3="CORREÇÃO NÃO ACEITE",TODAY()-J3,"") | T3: =IF(K3="A VERIFICAR",TODAY()-J3,"") | V3: =COUNTIF(S1:S5516, "<=30") -> 0 | W3: =COUNTIF(S1:S5516, ">=31")-COUNTIF(S1:S5516, ">60") -> 0 | X3: =COUNTIF(S1:S5516, ">60") -> 0 | Y3: =SUM(V3:X3) -> 0
A4: 45499 | B4: A | C4: A | D4: -1 | E4: a | F4: 3 | G4: Fixar parte plástica do exaustor | H4: AR | K4: REPARADO | L4: 45322 | N4: 45656 | O4: Solange calado - 91 4719646 | P4: =IF(K4="NÃO INTERVENCIONADO",TODAY()-J4,"") | Q4: =IF(K4="ENCOMENDADO",TODAY()-J4,"") | R4: =IF(K4="EM OBRA",TODAY()-J4,"") | S4: =IF(K4="CORREÇÃO NÃO ACEITE",TODAY()-J4,"") | T4: =IF(K4="A VERIFICAR",TODAY()-J4,"") | V4: Menos de 30 dias | W4: de 31 a 60 dias | X4: mais de 60 dias | Y4: Total
A5: 45499 | B5: A | C5: A | D5: -1 | E5: a | F5: 4 | G5: Tambor da máquina da roupa com ferrugem | H5: Cozimafra | K5: REPARADO | L5: 45322 | N5: 45656 | O5: Solange calado - 91 4719646 | P5: =IF(K5="NÃO INTERVENCIONADO",TODAY()-J5,"") | Q5: =IF(K5="ENCOMENDADO",TODAY()-J5,"") | R5: =IF(K5="EM OBRA",TODAY()-J5,"") | S5: =IF(K5="CORREÇÃO NÃO ACEITE",TODAY()-J5,"") | T5: =IF(K5="A VERIFICAR",TODAY()-J5,"") | V5: ANTIGIDADE - CORREÇÃO NÃO ACEITE
A6: 45499 | B6: A | C6: A | D6: -1 | E6: a | F6: 5 | G6: Porta da máquina da louça riscada | H6: AR | K6: REPARADO | L6: 45322 | N6: 45656 | O6: Solange calado - 91 4719646 | P6: =IF(K6="NÃO INTERVENCIONADO",TODAY()-J6,"") | Q6: =IF(K6="ENCOMENDADO",TODAY()-J6,"") | R6: =IF(K6="EM OBRA",TODAY()-J6,"") | S6: =IF(K6="CORREÇÃO NÃO ACEITE",TODAY()-J6,"") | T6: =IF(K6="A VERIFICAR",TODAY()-J6,"")
A7: 45499 | B7: A | C7: A | D7: -1 | E7: a | F7: 6 | G7: Afinar puxador | H7: Serrialu | K7: REPARADO | L7: 45322 | N7: 45540 | O7: Solange calado - 91 4719646 | P7: =IF(K7="NÃO INTERVENCIONADO",TODAY()-J7,"") | Q7: =IF(K7="ENCOMENDADO",TODAY()-J7,"") | R7: =IF(K7="EM OBRA",TODAY()-J7,"") | S7: =IF(K7="CORREÇÃO NÃO ACEITE",TODAY()-J7,"") | T7: =IF(K7="A VERIFICAR",TODAY()-J7,"") | V7: =COUNTIF(R1:R5524, "<=30") -> 0 | W7: =COUNTIF(R1:R5524, ">=31")-COUNTIF(R1:R5524, ">60") -> 0 | X7: =COUNTIF(R1:R5524, ">60") -> 0 | Y7: =SUM(V7:X7) -> 0
A8: 45499 | B8: A | C8: A | D8: -1 | E8: a | F8: 7 | G8: Afinar portas dos roupeiros | H8: AR | K8: REPARADO | L8: 45322 | N8: 45540 | O8: Solange calado - 91 4719646 | P8: =IF(K8="NÃO INTERVENCIONADO",TODAY()-J8,"") | Q8: =IF(K8="ENCOMENDADO",TODAY()-J8,"") | R8: =IF(K8="EM OBRA",TODAY()-J8,"") | S8: =IF(K8="CORREÇÃO NÃO ACEITE",TODAY()-J8,"") | T8: =IF(K8="A VERIFICAR",TODAY()-J8,"") | V8: Menos de 30 dias | W8: de 31 a 60 dias | X8: mais de 60 dias | Y8: Total
A9: 45499 | B9: A | C9: A | D9: -1 | E9: a | F9: 8 | G9: Pintura na guarnição do roupeiro onde a porta raspa | H9: AR | K9: REPARADO | L9: 45322 | N9: 45540 | O9: Solange calado - 91 4719646 | P9: =IF(K9="NÃO INTERVENCIONADO",TODAY()-J9,"") | Q9: =IF(K9="ENCOMENDADO",TODAY()-J9,"") | R9: =IF(K9="EM OBRA",TODAY()-J9,"") | S9: =IF(K9="CORREÇÃO NÃO ACEITE",TODAY()-J9,"") | T9: =IF(K9="A VERIFICAR",TODAY()-J9,"") | V9: ANTIGIDADE - EM OBRA
A10: 45499 | B10: A | C10: A | D10: -1 | E10: a | F10: 9 | G10: Campainha não funciona- Agendar com a MEO | H10: IEOL/MEO | J10: 45526 | K10: REPARADO | L10: 45322 | N10: 45572 | O10: Solange calado - 91 4719646 | P10: =IF(K10="NÃO INTERVENCIONADO",TODAY()-J10,"") | Q10: =IF(K10="ENCOMENDADO",TODAY()-J10,"") | R10: =IF(K10="EM OBRA",TODAY()-J10,"") | S10: =IF(K10="CORREÇÃO NÃO ACEITE",TODAY()-J10,"") | T10: =IF(K10="A VERIFICAR",TODAY()-J10,"")
A11: 45499 | B11: A | C11: A | D11: -1 | E11: a | F11: 10 | G11: Válvula do Bidé deixa passar água | H11: AR | J11: 45526 | K11: REPARADO | L11: 45322 | N11: 45601 | O11: Solange calado - 91 4719646 | P11: =IF(K11="NÃO INTERVENCIONADO",TODAY()-J11,"") | Q11: =IF(K11="ENCOMENDADO",TODAY()-J11,"") | R11: =IF(K11="EM OBRA",TODAY()-J11,"") | S11: =IF(K11="CORREÇÃO NÃO ACEITE",TODAY()-J11,"") | T11: =IF(K11="A VERIFICAR",TODAY()-J11,"") | V11: =COUNTIF(Q3:Q5531, "<=30") -> 0 | W11: =COUNTIF(Q3:Q5531, ">=31")-COUNTIF(Q3:Q5531, ">60") -> 0 | X11: =COUNTIF(Q3:Q5531, ">60") -> 0 | Y11: =SUM(V11:X11) -> 0
A12: 45499 | B12: A | C12: A | D12: -1 | E12: a | F12: 11 | G12: Moldura do Micro Ondas tem ferrugem | H12: Bosch | J12: 45526 | K12: REPARADO | L12: 45322 | N12: 45645 | O12: Solange calado - 91 4719646 | P12: =IF(K12="NÃO INTERVENCIONADO",TODAY()-J12,"") | Q12: =IF(K12="ENCOMENDADO",TODAY()-J12,"") | R12: =IF(K12="EM OBRA",TODAY()-J12,"") | S12: =IF(K12="CORREÇÃO NÃO ACEITE",TODAY()-J12,"") | T12: =IF(K12="A VERIFICAR",TODAY()-J12,"") | V12: Menos de 30 dias | W12: de 31 a 60 dias | X12: mais de 60 dias | Y12: Total
A13: 45499 | B13: A | C13: A | D13: -1 | E13: a | F13: 12 | G13: Chão da sala tem falhas em algumas lâminas e riscos | H13: Silvas | J13: 45526 | K13: REPARADO | L13: 45322 | N13: 45590 | O13: Solange calado - 91 4719646 | P13: =IF(K13="NÃO INTERVENCIONADO",TODAY()-J13,"") | Q13: =IF(K13="ENCOMENDADO",TODAY()-J13,"") | R13: =IF(K13="EM OBRA",TODAY()-J13,"") | S13: =IF(K13="CORREÇÃO NÃO ACEITE",TODAY()-J13,"") | T13: =IF(K13="A VERIFICAR",TODAY()-J13,"") | V13: ANTIGIDADE - ENCOMENDADO
A14: 45499 | B14: A | C14: A | D14: -1 | E14: a | F14: 13 | G14: Rodapé e moldura da porta da cozinha “estalou” | H14: Valco | J14: 45526 | K14: REPARADO | L14: 45322 | N14: 45594 | O14: Solange calado - 91 4719646 | P14: =IF(K14="NÃO INTERVENCIONADO",TODAY()-J14,"") | Q14: =IF(K14="ENCOMENDADO",TODAY()-J14,"") | R14: =IF(K14="EM OBRA",TODAY()-J14,"") | S14: =IF(K14="CORREÇÃO NÃO ACEITE",TODAY()-J14,"") | T14: =IF(K14="A VERIFICAR",TODAY()-J14,"")
A15: 45499 | B15: A | C15: A | D15: -1 | E15: a | F15: 15 | G15: Retificação/preenchimento das juntas dos azuleijos no wc | H15: AR | J15: 45568 | K15: REPARADO | L15: 45322 | N15: 45594 | O15: Solange calado - 91 4719646 | P15: =IF(K15="NÃO INTERVENCIONADO",TODAY()-J15,"") | Q15: =IF(K15="ENCOMENDADO",TODAY()-J15,"") | R15: =IF(K15="EM OBRA",TODAY()-J15,"") | S15: =IF(K15="CORREÇÃO NÃO ACEITE",TODAY()-J15,"") | T15: =IF(K15="A VERIFICAR",TODAY()-J15,"") | V15: Menos de 30 dias | W15: de 31 a 60 dias | X15: mais de 60 dias | Y15: Total
A16: 45499 | B16: A | C16: A | D16: -1 | E16: a | F16: 16 | G16: Limpeza do apartamento, que foi entregue imundo e até cinza de cigarro tinha em cima da máquina de lavar roupa | H16: AR | J16: 45568 | K16: REPARADO | L16: 45322 | N16: 45594 | O16: Solange calado - 91 4719646 | P16: =IF(K16="NÃO INTERVENCIONADO",TODAY()-J16,"") | Q16: =IF(K16="ENCOMENDADO",TODAY()-J16,"") | R16: =IF(K16="EM OBRA",TODAY()-J16,"") | S16: =IF(K16="CORREÇÃO NÃO ACEITE",TODAY()-J16,"") | T16: =IF(K16="A VERIFICAR",TODAY()-J16,"") | V16: ANTIGIDADE - NÃO INTERVENCIONADO
A17: 45499 | B17: A | C17: A | D17: -1 | E17: a | F17: 17 | G17: Limpeza dos vidros e proteção de alumínio das janelas | H17: AR | J17: 45568 | K17: REPARADO | L17: 45322 | N17: 45594 | O17: Solange calado - 91 4719646 | P17: =IF(K17="NÃO INTERVENCIONADO",TODAY()-J17,"") | Q17: =IF(K17="ENCOMENDADO",TODAY()-J17,"") | R17: =IF(K17="EM OBRA",TODAY()-J17,"") | S17: =IF(K17="CORREÇÃO NÃO ACEITE",TODAY()-J17,"") | T17: =IF(K17="A VERIFICAR",TODAY()-J17,"")
A18: 45499 | B18: A | C18: A | D18: -1 | E18: a | F18: 18 | G18: Bicha mal apertada | H18: AR | J18: 45615 | K18: REPARADO | L18: 45322 | N18: 45615 | O18: Solange calado - 91 4719646 | P18: =IF(K18="NÃO INTERVENCIONADO",TODAY()-J18,"") | Q18: =IF(K18="ENCOMENDADO",TODAY()-J18,"") | R18: =IF(K18="EM OBRA",TODAY()-J18,"") | S18: =IF(K18="CORREÇÃO NÃO ACEITE",TODAY()-J18,"") | T18: =IF(K18="A VERIFICAR",TODAY()-J18,"")
A19: 45499 | B19: A | C19: A | D19: -1 | E19: a | F19: 19 | G19: Pintura da parede atrás da porta da entrada | H19: AR | J19: 45568 | K19: REPARADO | L19: 45322 | N19: 45601 | O19: Solange calado - 91 4719646 | P19: =IF(K19="NÃO INTERVENCIONADO",TODAY()-J19,"") | Q19: =IF(K19="ENCOMENDADO",TODAY()-J19,"") | R19: =IF(K19="EM OBRA",TODAY()-J19,"") | S19: =IF(K19="CORREÇÃO NÃO ACEITE",TODAY()-J19,"") | T19: =IF(K19="A VERIFICAR",TODAY()-J19,"") | V19: =COUNTIF(P15:P5538, "<=30") -> 0 | W19: =COUNTIF(P15:P5538, ">=31")-COUNTIF(P15:P5538, ">60") -> 0 | X19: =COUNTIF(P15:P5538, ">60") -> 1 | Y19: =SUM(V19:X19) -> 1
A20: 45517 | B20: AB | C20: B | D20: -1 | E20: b | F20: 1 | G20: Porta arrecadação com amolgado | H20: Sweet Door | K20: REPARADO | L20: 45481 | N20: 45582 | O20: Tiago Correia - 965579733 | P20: =IF(K20="NÃO INTERVENCIONADO",TODAY()-J20,"") | Q20: =IF(K20="ENCOMENDADO",TODAY()-J20,"") | R20: =IF(K20="EM OBRA",TODAY()-J20,"") | S20: =IF(K20="CORREÇÃO NÃO ACEITE",TODAY()-J20,"") | T20: =IF(K20="A VERIFICAR",TODAY()-J20,"")
A21: 45517 | B21: AB | C21: B | D21: -1 | E21: b | F21: 2 | G21: Melhorar pintura apartamento 2ª mão tinta geral | H21: AR | K21: REPARADO | L21: 45481 | N21: 45656 | O21: Tiago Correia - 965579733 | P21: =IF(K21="NÃO INTERVENCIONADO",TODAY()-J21,"") | Q21: =IF(K21="ENCOMENDADO",TODAY()-J21,"") | R21: =IF(K21="EM OBRA",TODAY()-J21,"") | S21: =IF(K21="CORREÇÃO NÃO ACEITE",TODAY()-J21,"") | T21: =IF(K21="A VERIFICAR",TODAY()-J21,"")
A22: 45517 | B22: AB | C22: B | D22: -1 | E22: b | F22: 3 | G22: Fissura na parede | H22: AR | K22: REPARADO | L22: 45481 | N22: 45656 | O22: Tiago Correia - 965579733 | P22: =IF(K22="NÃO INTERVENCIONADO",TODAY()-J22,"") | Q22: =IF(K22="ENCOMENDADO",TODAY()-J22,"") | R22: =IF(K22="EM OBRA",TODAY()-J22,"") | S22: =IF(K22="CORREÇÃO NÃO ACEITE",TODAY()-J22,"") | T22: =IF(K22="A VERIFICAR",TODAY()-J22,"")
A23: 45517 | B23: AB | C23: B | D23: -1 | E23: b | F23: 4 | G23: Melhorar remate porta /parede/fissura | H23: AR | K23: REPARADO | L23: 45481 | N23: 45656 | O23: Tiago Correia - 965579733 | P23: =IF(K23="NÃO INTERVENCIONADO",TODAY()-J23,"") | Q23: =IF(K23="ENCOMENDADO",TODAY()-J23,"") | R23: =IF(K23="EM OBRA",TODAY()-J23,"") | S23: =IF(K23="CORREÇÃO NÃO ACEITE",TODAY()-J23,"") | T23: =IF(K23="A VERIFICAR",TODAY()-J23,"")
A24: 45517 | B24: AB | C24: B | D24: -1 | E24: b | F24: 5 | G24: Melhorar remate rodape /parede/fissura | H24: AR | K24: REPARADO | L24: 45481 | N24: 45656 | O24: Tiago Correia - 965579733 | P24: =IF(K24="NÃO INTERVENCIONADO",TODAY()-J24,"") | Q24: =IF(K24="ENCOMENDADO",TODAY()-J24,"") | R24: =IF(K24="EM OBRA",TODAY()-J24,"") | S24: =IF(K24="CORREÇÃO NÃO ACEITE",TODAY()-J24,"") | T24: =IF(K24="A VERIFICAR",TODAY()-J24,"")
A25: 45517 | B25: AB | C25: B | D25: -1 | E25: b | F25: 6 | G25: Paredes sujas geral | H25: AR | K25: REPARADO | L25: 45481 | N25: 45656 | O25: Tiago Correia - 965579733 | P25: =IF(K25="NÃO INTERVENCIONADO",TODAY()-J25,"") | Q25: =IF(K25="ENCOMENDADO",TODAY()-J25,"") | R25: =IF(K25="EM OBRA",TODAY()-J25,"") | S25: =IF(K25="CORREÇÃO NÃO ACEITE",TODAY()-J25,"") | T25: =IF(K25="A VERIFICAR",TODAY()-J25,"")
A26: 45517 | B26: AB | C26: B | D26: -1 | E26: b | F26: 7 | G26: Folha porta correr entra parede/batente | H26: Globaldis | K26: REPARADO | L26: 45481 | N26: 45656 | O26: Tiago Correia - 965579733 | P26: =IF(K26="NÃO INTERVENCIONADO",TODAY()-J26,"") | Q26: =IF(K26="ENCOMENDADO",TODAY()-J26,"") | R26: =IF(K26="EM OBRA",TODAY()-J26,"") | S26: =IF(K26="CORREÇÃO NÃO ACEITE",TODAY()-J26,"") | T26: =IF(K26="A VERIFICAR",TODAY()-J26,"")
A27: 45517 | B27: AB | C27: B | D27: -1 | E27: b | F27: 8 | G27: Piso cozinha com juntas desalinhadas /Partidos na peça | H27: AR | K27: REPARADO | L27: 45481 | N27: 45656 | O27: Tiago Correia - 965579733 | P27: =IF(K27="NÃO INTERVENCIONADO",TODAY()-J27,"") | Q27: =IF(K27="ENCOMENDADO",TODAY()-J27,"") | R27: =IF(K27="EM OBRA",TODAY()-J27,"") | S27: =IF(K27="CORREÇÃO NÃO ACEITE",TODAY()-J27,"") | T27: =IF(K27="A VERIFICAR",TODAY()-J27,"")
A28: 45517 | B28: AB | C28: B | D28: -1 | E28: b | F28: 9 | G28: Pedra soleira suja | H28: AR | K28: REPARADO | L28: 45481 | N28: 45656 | O28: Tiago Correia - 965579733 | P28: =IF(K28="NÃO INTERVENCIONADO",TODAY()-J28,"") | Q28: =IF(K28="ENCOMENDADO",TODAY()-J28,"") | R28: =IF(K28="EM OBRA",TODAY()-J28,"") | S28: =IF(K28="CORREÇÃO NÃO ACEITE",TODAY()-J28,"") | T28: =IF(K28="A VERIFICAR",TODAY()-J28,"")
A29: 45517 | B29: AB | C29: B | D29: -1 | E29: b | F29: 10 | G29: Refazer silicone caixa estore/fissura | H29: AR | K29: REPARADO | L29: 45481 | N29: 45656 | O29: Tiago Correia - 965579733 | P29: =IF(K29="NÃO INTERVENCIONADO",TODAY()-J29,"") | Q29: =IF(K29="ENCOMENDADO",TODAY()-J29,"") | R29: =IF(K29="EM OBRA",TODAY()-J29,"") | S29: =IF(K29="CORREÇÃO NÃO ACEITE",TODAY()-J29,"") | T29: =IF(K29="A VERIFICAR",TODAY()-J29,"")
A30: 45517 | B30: AB | C30: B | D30: -1 | E30: b | F30: 11 | G30: Guarda da janela do quarto danificada (substituir ) - 1,03x0,62 | H30: Serrialu | K30: REPARADO | L30: 45481 | N30: 45656 | O30: Tiago Correia - 965579733 | P30: =IF(K30="NÃO INTERVENCIONADO",TODAY()-J30,"") | Q30: =IF(K30="ENCOMENDADO",TODAY()-J30,"") | R30: =IF(K30="EM OBRA",TODAY()-J30,"") | S30: =IF(K30="CORREÇÃO NÃO ACEITE",TODAY()-J30,"") | T30: =IF(K30="A VERIFICAR",TODAY()-J30,"")
A31: 45517 | B31: AB | C31: B | D31: -1 | E31: b | F31: 12 | G31: A janela do WC não abre em condiçóes devido a tampa da caixa de estore | H31: Serrialu | K31: REPARADO | L31: 45481 | N31: 45656 | O31: Tiago Correia - 965579733 | P31: =IF(K31="NÃO INTERVENCIONADO",TODAY()-J31,"") | Q31: =IF(K31="ENCOMENDADO",TODAY()-J31,"") | R31: =IF(K31="EM OBRA",TODAY()-J31,"") | S31: =IF(K31="CORREÇÃO NÃO ACEITE",TODAY()-J31,"") | T31: =IF(K31="A VERIFICAR",TODAY()-J31,"")
... A34: 45517 | B34: AB | C34: B | D34: -1 | E34: b | F34: 16 | G34: Porta de entrada precis de afinação | H34: Sweet Door | K34: REPARADO | L34: 45481 | N34: 45555 | O34: Tiago Correia - 965579733 | P34: =IF(K34="NÃO INTERVENCIONADO",TODAY()-J34,"") | Q34: =IF(K34="ENCOMENDADO",TODAY()-J34,"") | R34: =IF(K34="EM OBRA",TODAY()-J34,"") | S34: =IF(K34="CORREÇÃO NÃO ACEITE",TODAY()-J34,"") | T34: =IF(K34="A VERIFICAR",TODAY()-J34,"")
A35: 45517 | B35: AB | C35: B | D35: -1 | E35: b | F35: 17 | G35: janela da cozinha carece de afinação resultante da dificuldade em fechar a mesma | H35: Serrialu | J35: 45551 | K35: REPARADO | L35: 45481 | N35: 45565 | O35: Tiago Correia - 965579733 | P35: =IF(K35="NÃO INTERVENCIONADO",TODAY()-J35,"") | Q35: =IF(K35="ENCOMENDADO",TODAY()-J35,"") | R35: =IF(K35="EM OBRA",TODAY()-J35,"") | S35: =IF(K35="CORREÇÃO NÃO ACEITE",TODAY()-J35,"") | T35: =IF(K35="A VERIFICAR",TODAY()-J35,"")
A36: 45517 | B36: AB | C36: B | D36: -1 | E36: b | F36: 18 | G36: chapa interior da porta de entrada do imóvel danificada | H36: Sweet Door | J36: 45551 | K36: REPARADO | L36: 45481 | N36: 45565 | O36: Tiago Correia - 965579733 | P36: =IF(K36="NÃO INTERVENCIONADO",TODAY()-J36,"") | Q36: =IF(K36="ENCOMENDADO",TODAY()-J36,"") | R36: =IF(K36="EM OBRA",TODAY()-J36,"") | S36: =IF(K36="CORREÇÃO NÃO ACEITE",TODAY()-J36,"") | T36: =IF(K36="A VERIFICAR",TODAY()-J36,"")
A37: 45517 | B37: AB | C37: B | D37: -1 | E37: b | F37: 19 | G37: Tomada da sala queimada | H37: IEOL | J37: 45551 | K37: REPARADO | L37: 45481 | N37: 45565 | O37: Tiago Correia - 965579733 | P37: =IF(K37="NÃO INTERVENCIONADO",TODAY()-J37,"") | Q37: =IF(K37="ENCOMENDADO",TODAY()-J37,"") | R37: =IF(K37="EM OBRA",TODAY()-J37,"") | S37: =IF(K37="CORREÇÃO NÃO ACEITE",TODAY()-J37,"") | T37: =IF(K37="A VERIFICAR",TODAY()-J37,"")
A38: 45517 | B38: AB | C38: B | D38: -1 | E38: b | F38: 20 | G38: Banheira sem água quente e com pouca pressão na agua fria | H38: AR | J38: 45551 | K38: REPARADO | L38: 45481 | N38: 45565 | O38: Tiago Correia - 965579733 | P38: =IF(K38="NÃO INTERVENCIONADO",TODAY()-J38,"") | Q38: =IF(K38="ENCOMENDADO",TODAY()-J38,"") | R38: =IF(K38="EM OBRA",TODAY()-J38,"") | S38: =IF(K38="CORREÇÃO NÃO ACEITE",TODAY()-J38,"") | T38: =IF(K38="A VERIFICAR",TODAY()-J38,"")
A39: 45517 | B39: AB | C39: B | D39: -1 | E39: b | F39: 21 | G39: Substituir pavimento de uma divisão inteira | H39: Silvas | J39: 45559 | K39: REPARADO | L39: 45481 | N39: 45559 | O39: Tiago Correia - 965579733 | P39: =IF(K39="NÃO INTERVENCIONADO",TODAY()-J39,"") | Q39: =IF(K39="ENCOMENDADO",TODAY()-J39,"") | R39: =IF(K39="EM OBRA",TODAY()-J39,"") | S39: =IF(K39="CORREÇÃO NÃO ACEITE",TODAY()-J39,"") | T39: =IF(K39="A VERIFICAR",TODAY()-J39,"")
A40: 45517 | B40: AB | C40: B | D40: -1 | E40: b | F40: 22 | G40: substituição da porta arrecadação | H40: Sweet Door | J40: 45565 | K40: REPARADO | L40: 45481 | N40: 45582 | O40: Tiago Correia - 965579733 | P40: =IF(K40="NÃO INTERVENCIONADO",TODAY()-J40,"") | Q40: =IF(K40="ENCOMENDADO",TODAY()-J40,"") | R40: =IF(K40="EM OBRA",TODAY()-J40,"") | S40: =IF(K40="CORREÇÃO NÃO ACEITE",TODAY()-J40,"") | T40: =IF(K40="A VERIFICAR",TODAY()-J40,"")
A41: 45517 | B41: AB | C41: B | D41: -1 | E41: b | F41: 23 | G41: substituição da porta do roupeiro | H41: Globaldis | J41: 45565 | K41: REPARADO | L41: 45481 | N41: 45681 | O41: Tiago Correia - 965579733 | P41: =IF(K41="NÃO INTERVENCIONADO",TODAY()-J41,"") | Q41: =IF(K41="ENCOMENDADO",TODAY()-J41,"") | R41: =IF(K41="EM OBRA",TODAY()-J41,"") | S41: =IF(K41="CORREÇÃO NÃO ACEITE",TODAY()-J41,"") | T41: =IF(K41="A VERIFICAR",TODAY()-J41,"")
A42: 45517 | B42: AB | C42: B | D42: -1 | E42: b | F42: 24 | G42: instalação de solução que evite o fecho completo da porta (em cassete) da cozinha. | H42: Globaldis | J42: 45607 | K42: REPARADO | L42: 45481 | N42: 45653 | O42: Tiago Correia - 965579733 | P42: =IF(K42="NÃO INTERVENCIONADO",TODAY()-J42,"") | Q42: =IF(K42="ENCOMENDADO",TODAY()-J42,"") | R42: =IF(K42="EM OBRA",TODAY()-J42,"") | S42: =IF(K42="CORREÇÃO NÃO ACEITE",TODAY()-J42,"") | T42: =IF(K42="A VERIFICAR",TODAY()-J42,"")
A43: 45517 | B43: AB | C43: B | D43: -1 | E43: b | F43: 25 | G43: luz de teto do quarto não trm corrente elétrica | H43: IEOL | J43: 45565 | K43: REPARADO | L43: 45481 | N43: 45565 | O43: Tiago Correia - 965579733 | P43: =IF(K43="NÃO INTERVENCIONADO",TODAY()-J43,"") | Q43: =IF(K43="ENCOMENDADO",TODAY()-J43,"") | R43: =IF(K43="EM OBRA",TODAY()-J43,"") | S43: =IF(K43="CORREÇÃO NÃO ACEITE",TODAY()-J43,"") | T43: =IF(K43="A VERIFICAR",TODAY()-J43,"")
A44: 45517 | B44: AB | C44: B | D44: -1 | E44: b | F44: 26 | G44: tomada da sala (parede do ac) nao tem corrente - comutador | H44: IEOL | J44: 45565 | K44: REPARADO | L44: 45481 | N44: 45565 | O44: Tiago Correia - 965579733 | P44: =IF(K44="NÃO INTERVENCIONADO",TODAY()-J44,"") | Q44: =IF(K44="ENCOMENDADO",TODAY()-J44,"") | R44: =IF(K44="EM OBRA",TODAY()-J44,"") | S44: =IF(K44="CORREÇÃO NÃO ACEITE",TODAY()-J44,"") | T44: =IF(K44="A VERIFICAR",TODAY()-J44,"")
A45: 45517 | B45: AB | C45: B | D45: -1 | E45: b | F45: 27 | G45: bidé pinga água insistentemente | H45: AR | J45: 45565 | K45: REPARADO | L45: 45481 | N45: 45582 | O45: Tiago Correia - 965579733 | P45: =IF(K45="NÃO INTERVENCIONADO",TODAY()-J45,"") | Q45: =IF(K45="ENCOMENDADO",TODAY()-J45,"") | R45: =IF(K45="EM OBRA",TODAY()-J45,"") | S45: =IF(K45="CORREÇÃO NÃO ACEITE",TODAY()-J45,"") | T45: =IF(K45="A VERIFICAR",TODAY()-J45,"") | V45: =COUNTIF(P21:T5509, "<=30") -> 0 | W45: =COUNTIF(P21:T5509, ">=31")-COUNTIF(P21:T5509, ">60") -> 0 | X45: =COUNTIF(P21:T5509, ">60") -> 1 | Y45: =SUM(V45:X45) -> 1
A46: 45517 | B46: AB | C46: B | D46: -1 | E46: b | F46: 28 | G46: misturadora da banheira não faz a mistura de água quente com água fria | H46: AR | J46: 45565 | K46: REPARADO | L46: 45481 | N46: 45565 | O46: Tiago Correia - 965579733 | P46: =IF(K46="NÃO INTERVENCIONADO",TODAY()-J46,"") | Q46: =IF(K46="ENCOMENDADO",TODAY()-J46,"") | R46: =IF(K46="EM OBRA",TODAY()-J46,"") | S46: =IF(K46="CORREÇÃO NÃO ACEITE",TODAY()-J46,"") | T46: =IF(K46="A VERIFICAR",TODAY()-J46,"") | V46: Menos de 30 dias | W46: de 31 a 60 dias | X46: mais de 60 dias | Y46: Total
A47: 45517 | B47: AB | C47: B | D47: -1 | E47: b | F47: 29 | H47: AR | J47: 45565 | K47: REPARADO | L47: 45481 | N47: 45565 | O47: Tiago Correia - 965579733 | P47: =IF(K47="NÃO INTERVENCIONADO",TODAY()-J47,"") | Q47: =IF(K47="ENCOMENDADO",TODAY()-J47,"") | R47: =IF(K47="EM OBRA",TODAY()-J47,"") | S47: =IF(K47="CORREÇÃO NÃO ACEITE",TODAY()-J47,"") | T47: =IF(K47="A VERIFICAR",TODAY()-J47,"") | V47: TOTAL
A48: 45517 | B48: AB | C48: B | D48: -1 | E48: b | F48: 30 | G48: Tirar porta e colocar | H48: AR | J48: 45593 | K48: REPARADO | L48: 45481 | N48: 45593 | O48: Tiago Correia - 965579733 | P48: =IF(K48="NÃO INTERVENCIONADO",TODAY()-J48,"") | Q48: =IF(K48="ENCOMENDADO",TODAY()-J48,"") | R48: =IF(K48="EM OBRA",TODAY()-J48,"") | S48: =IF(K48="CORREÇÃO NÃO ACEITE",TODAY()-J48,"") | T48: =IF(K48="A VERIFICAR",TODAY()-J48,"")
A49: 45517 | B49: AB | C49: B | D49: -1 | E49: b | F49: 31 | G49: Armário da casa de banho caiu no chão | H49: Globaldis | J49: 45609 | K49: REPARADO | L49: 45481 | N49: 45644 | O49: Tiago Correia - 965579733 | P49: =IF(K49="NÃO INTERVENCIONADO",TODAY()-J49,"") | Q49: =IF(K49="ENCOMENDADO",TODAY()-J49,"") | R49: =IF(K49="EM OBRA",TODAY()-J49,"") | S49: =IF(K49="CORREÇÃO NÃO ACEITE",TODAY()-J49,"") | T49: =IF(K49="A VERIFICAR",TODAY()-J49,"") | V49: =COUNTIF(T29:T5517, "<=30") -> 0 | W49: =COUNTIF(T29:T5517, ">=31")-COUNTIF(T29:T5517, ">60") -> 0 | X49: =COUNTIF(T29:T5517, ">60") -> 0 | Y49: =SUM(V49:X49) -> 0
A50: 45517 | B50: AB | C50: B | D50: -1 | E50: b | F50: 32 | G50: Estores da cozinha desce até a meio da janela e depois cai por completo | H50: Nacional Blinds | J50: 45596 | K50: REPARADO | L50: 45481 | N50: 45601 | O50: Tiago Correia - 965579733 | P50: =IF(K50="NÃO INTERVENCIONADO",TODAY()-J50,"") | Q50: =IF(K50="ENCOMENDADO",TODAY()-J50,"") | R50: =IF(K50="EM OBRA",TODAY()-J50,"") | S50: =IF(K50="CORREÇÃO NÃO ACEITE",TODAY()-J50,"") | T50: =IF(K50="A VERIFICAR",TODAY()-J50,"") | V50: Menos de 30 dias | W50: de 31 a 60 dias | X50: mais de 60 dias | Y50: Total
A51: 45517 | B51: AB | C51: B | D51: -1 | E51: b | F51: 33 | G51: Roupeiro (2,00m x 0,505) | H51: Globaldis | J51: 45708 | K51: REPARADO | L51: 45481 | M51: 45707 | N51: 45811
A52: 45617 | B52: AC | C52: B | D52: -1 | E52: c | F52: 1 | G52: Torneira do lavatório picada - Tem de ser trocadas | H52: AR | J52: 45623 | K52: REPARADO | L52: 45399 | N52: 45681 | P52: =IF(K52="NÃO INTERVENCIONADO",TODAY()-J52,"") | Q52: =IF(K52="ENCOMENDADO",TODAY()-J52,"") | R52: =IF(K52="EM OBRA",TODAY()-J52,"") | S52: =IF(K52="CORREÇÃO NÃO ACEITE",TODAY()-J52,"") | T52: =IF(K52="A VERIFICAR",TODAY()-J52,"")
A53: 45617 | B53: AC | C53: B | D53: -1 | E53: c | F53: 2 | G53: Espelho estalado na aresta esquerda 1,38x1,20 | H53: Espaço Vidro | K53: REPARADO | L53: 45399 | N53: 45548 | P53: =IF(K53="NÃO INTERVENCIONADO",TODAY()-J53,"") | Q53: =IF(K53="ENCOMENDADO",TODAY()-J53,"") | R53: =IF(K53="EM OBRA",TODAY()-J53,"") | S53: =IF(K53="CORREÇÃO NÃO ACEITE",TODAY()-J53,"") | T53: =IF(K53="A VERIFICAR",TODAY()-J53,"")
A54: 45617 | B54: AC | C54: B | D54: -1 | E54: c | F54: 3 | G54: Pedra da bancada com riscos IS | H54: Pardal | K54: REPARADO | L54: 45399 | N54: 45616 | P54: =IF(K54="NÃO INTERVENCIONADO",TODAY()-J54,"") | Q54: =IF(K54="ENCOMENDADO",TODAY()-J54,"") | R54: =IF(K54="EM OBRA",TODAY()-J54,"") | S54: =IF(K54="CORREÇÃO NÃO ACEITE",TODAY()-J54,"") | T54: =IF(K54="A VERIFICAR",TODAY()-J54,"")
A55: 45617 | B55: AC | C55: B | D55: -1 | E55: c | F55: 4 | G55: Juntas do pavimento amarelas | H55: AR | J55: 45623 | K55: REPARADO | L55: 45399 | N55: 45681 | P55: =IF(K55="NÃO INTERVENCIONADO",TODAY()-J55,"") | Q55: =IF(K55="ENCOMENDADO",TODAY()-J55,"") | R55: =IF(K55="EM OBRA",TODAY()-J55,"") | S55: =IF(K55="CORREÇÃO NÃO ACEITE",TODAY()-J55,"") | T55: =IF(K55="A VERIFICAR",TODAY()-J55,"")
A56: 45617 | B56: AC | C56: B | D56: -1 | E56: c | F56: 5 | G56: Sanita com parafuso solto por baixo - vente agua por baixo | H56: Luzimeca | K56: REPARADO | L56: 45399 | N56: 45656 | P56: =IF(K56="NÃO INTERVENCIONADO",TODAY()-J56,"") | Q56: =IF(K56="ENCOMENDADO",TODAY()-J56,"") | R56: =IF(K56="EM OBRA",TODAY()-J56,"") | S56: =IF(K56="CORREÇÃO NÃO ACEITE",TODAY()-J56,"") | T56: =IF(K56="A VERIFICAR",TODAY()-J56,"")
A57: 45617 | B57: AC | C57: B | D57: -1 | E57: c | F57: 6 | G57: Bide com riscos | H57: AR | J57: 45623 | K57: REPARADO | L57: 45399 | N57: 45681 | P57: =IF(K57="NÃO INTERVENCIONADO",TODAY()-J57,"") | Q57: =IF(K57="ENCOMENDADO",TODAY()-J57,"") | R57: =IF(K57="EM OBRA",TODAY()-J57,"") | S57: =IF(K57="CORREÇÃO NÃO ACEITE",TODAY()-J57,"") | T57: =IF(K57="A VERIFICAR",TODAY()-J57,"")
A58: 45617 | B58: AC | C58: B | D58: -1 | E58: c | F58: 7 | G58: Puxador com ferrugem | H58: AR | K58: REPARADO | L58: 45399 | N58: 45656 | P58: =IF(K58="NÃO INTERVENCIONADO",TODAY()-J58,"") | Q58: =IF(K58="ENCOMENDADO",TODAY()-J58,"") | R58: =IF(K58="EM OBRA",TODAY()-J58,"") | S58: =IF(K58="CORREÇÃO NÃO ACEITE",TODAY()-J58,"") | T58: =IF(K58="A VERIFICAR",TODAY()-J58,"")
A59: 45617 | B59: AC | C59: B | D59: -1 | E59: c | F59: 8 | G59: Porta do armário picada com remendos | H59: Globaldis | K59: REPARADO | L59: 45399 | N59: 45471 | P59: =IF(K59="NÃO INTERVENCIONADO",TODAY()-J59,"") | Q59: =IF(K59="ENCOMENDADO",TODAY()-J59,"") | R59: =IF(K59="EM OBRA",TODAY()-J59,"") | S59: =IF(K59="CORREÇÃO NÃO ACEITE",TODAY()-J59,"") | T59: =IF(K59="A VERIFICAR",TODAY()-J59,"")
A60: 45617 | B60: AC | C60: B | D60: -1 | E60: c | F60: 9 | G60: Pavimento com manchas de humidade/negro | H60: Silvas | K60: REPARADO | L60: 45399 | N60: 45561 | P60: =IF(K60="NÃO INTERVENCIONADO",TODAY()-J60,"") | Q60: =IF(K60="ENCOMENDADO",TODAY()-J60,"") | R60: =IF(K60="EM OBRA",TODAY()-J60,"") | S60: =IF(K60="CORREÇÃO NÃO ACEITE",TODAY()-J60,"") | T60: =IF(K60="A VERIFICAR",TODAY()-J60,"")
A61: 45617 | B61: AC | C61: B | D61: -1 | E61: c | F61: 10 | G61: Aro da porta inchado | H61: Globaldis | K61: REPARADO | L61: 45399 | N61: 45608 | P61: =IF(K61="NÃO INTERVENCIONADO",TODAY()-J61,"") | Q61: =IF(K61="ENCOMENDADO",TODAY()-J61,"") | R61: =IF(K61="EM OBRA",TODAY()-J61,"") | S61: =IF(K61="CORREÇÃO NÃO ACEITE",TODAY()-J61,"") | T61: =IF(K61="A VERIFICAR",TODAY()-J61,"")
A62: 45617 | B62: AC | C62: B | D62: -1 | E62: c | F62: 11 | G62: Falta travão na porta de correr /concha | H62: Globaldis | K62: REPARADO | L62: 45399 | N62: 45608 | P62: =IF(K62="NÃO INTERVENCIONADO",TODAY()-J62,"") | Q62: =IF(K62="ENCOMENDADO",TODAY()-J62,"") | R62: =IF(K62="EM OBRA",TODAY()-J62,"") | S62: =IF(K62="CORREÇÃO NÃO ACEITE",TODAY()-J62,"") | T62: =IF(K62="A VERIFICAR",TODAY()-J62,"")
A63: 45617 | B63: AC | C63: B | D63: -1 | E63: c | F63: 12 | G63: Rodapé inchado | H63: Globaldis | K63: REPARADO | L63: 45399 | N63: 45608 | P63: =IF(K63="NÃO INTERVENCIONADO",TODAY()-J63,"") | Q63: =IF(K63="ENCOMENDADO",TODAY()-J63,"") | R63: =IF(K63="EM OBRA",TODAY()-J63,"") | S63: =IF(K63="CORREÇÃO NÃO ACEITE",TODAY()-J63,"") | T63: =IF(K63="A VERIFICAR",TODAY()-J63,"")
A64: 45617 | B64: AC | C64: B | D64: -1 | E64: c | F64: 13 | G64: Peça para tapar os parafusos da gaveta | H64: AR | K64: REPARADO | L64: 45399 | N64: 45608 | P64: =IF(K64="NÃO INTERVENCIONADO",TODAY()-J64,"") | Q64: =IF(K64="ENCOMENDADO",TODAY()-J64,"") | R64: =IF(K64="EM OBRA",TODAY()-J64,"") | S64: =IF(K64="CORREÇÃO NÃO ACEITE",TODAY()-J64,"") | T64: =IF(K64="A VERIFICAR",TODAY()-J64,"")
A65: 45617 | B65: AC | C65: B | D65: -1 | E65: c | F65: 14 | G65: Marca de puxador na parede | H65: AR | J65: 45623 | K65: REPARADO | L65: 45399 | N65: 45681 | P65: =IF(K65="NÃO INTERVENCIONADO",TODAY()-J65,"") | Q65: =IF(K65="ENCOMENDADO",TODAY()-J65,"") | R65: =IF(K65="EM OBRA",TODAY()-J65,"") | S65: =IF(K65="CORREÇÃO NÃO ACEITE",TODAY()-J65,"") | T65: =IF(K65="A VERIFICAR",TODAY()-J65,"")
A66: 45617 | B66: AC | C66: B | D66: -1 | E66: c | F66: 15 | G66: Riscos no pavimento | H66: Silvas | K66: REPARADO | L66: 45399 | N66: 45587 | P66: =IF(K66="NÃO INTERVENCIONADO",TODAY()-J66,"") | Q66: =IF(K66="ENCOMENDADO",TODAY()-J66,"") | R66: =IF(K66="EM OBRA",TODAY()-J66,"") | S66: =IF(K66="CORREÇÃO NÃO ACEITE",TODAY()-J66,"") | T66: =IF(K66="A VERIFICAR",TODAY()-J66,"")
A67: 45617 | B67: AC | C67: B | D67: -1 | E67: c | F67: 16 | G67: Trocar chão da cozinha | H67: AR | J67: 45616 | K67: REPARADO | L67: 45399 | N67: 45616 | P67: =IF(K67="NÃO INTERVENCIONADO",TODAY()-J67,"") | Q67: =IF(K67="ENCOMENDADO",TODAY()-J67,"") | R67: =IF(K67="EM OBRA",TODAY()-J67,"") | S67: =IF(K67="CORREÇÃO NÃO ACEITE",TODAY()-J67,"") | T67: =IF(K67="A VERIFICAR",TODAY()-J67,"")
A68: 45617 | B68: AC | C68: B | D68: -1 | E68: c | F68: 17 | G68: Fuga de água na zona da casa de banho (bidé) | H68: Luzimeca | J68: 46127 | K68: REPARADO | L68: 45399 | N68: 46141
A69: 45617 | B69: AC | C69: B | D69: -1 | E69: c | F69: 18 | G69: As próprias torneiras de passagem de água quente e fria, têm umafuga de água. | H69: AR | J69: 46127 | K69: A VERIFICAR | L69: 45399
A70: 45617 | B70: AC | C70: B | D70: -1 | E70: c | F70: 19 | G70: O tubo de escoamento da água do bidé também tem fuga. | H70: Luzimeca | J70: 46127 | K70: REPARADO | L70: 45399 | N70: 46141
A71: 45617 | B71: AC | C71: B | D71: -1 | E71: c | F71: 20 | G71: A janela do quarto e da sala estão a vedar mal e fecha mal, o que deixa a entrar ar vindo da rua e possivelmente deixa entrar água da chuva na possibilidade de chover. | H71: Serrialu | J71: 46115 | K71: REPARADO | L71: 45399 | N71: 46150
A72: 45561 | B72: AD | C72: B | D72: -1 | E72: a | F72: 1 | G72: Falta ponto de luz no teto | H72: IEOL | K72: REPARADO | L72: 45377 | N72: 45397 | P72: =IF(K72="NÃO INTERVENCIONADO",TODAY()-J72,"") | Q72: =IF(K72="ENCOMENDADO",TODAY()-J72,"") | R72: =IF(K72="EM OBRA",TODAY()-J72,"") | S72: =IF(K72="CORREÇÃO NÃO ACEITE",TODAY()-J72,"") | T72: =IF(K72="A VERIFICAR",TODAY()-J72,"")
A73: 45561 | B73: AD | C73: B | D73: -1 | E73: a | F73: 2 | G73: Luz não liga - não tem contador | H73: IEOL | K73: REPARADO | L73: 45377 | N73: 45610 | O73: Proprietario enviou email 14/11 10:58 a dizer que não há mais correções a fazer no apto | P73: =IF(K73="NÃO INTERVENCIONADO",TODAY()-J73,"") | Q73: =IF(K73="ENCOMENDADO",TODAY()-J73,"") | R73: =IF(K73="EM OBRA",TODAY()-J73,"") | S73: =IF(K73="CORREÇÃO NÃO ACEITE",TODAY()-J73,"") | T73: =IF(K73="A VERIFICAR",TODAY()-J73,"")
A74: 45561 | B74: AD | C74: B | D74: -1 | E74: a | F74: 3 | G74: Racha no teto e parede (retoque de pintura) | H74: AR | K74: REPARADO | L74: 45377 | N74: 45397 | P74: =IF(K74="NÃO INTERVENCIONADO",TODAY()-J74,"") | Q74: =IF(K74="ENCOMENDADO",TODAY()-J74,"") | R74: =IF(K74="EM OBRA",TODAY()-J74,"") | S74: =IF(K74="CORREÇÃO NÃO ACEITE",TODAY()-J74,"") | T74: =IF(K74="A VERIFICAR",TODAY()-J74,"")
A75: 45561 | B75: AD | C75: B | D75: -1 | E75: a | F75: 4 | G75: Mancha na pintura | H75: AR | K75: REPARADO | L75: 45377 | N75: 45397 | P75: =IF(K75="NÃO INTERVENCIONADO",TODAY()-J75,"") | Q75: =IF(K75="ENCOMENDADO",TODAY()-J75,"") | R75: =IF(K75="EM OBRA",TODAY()-J75,"") | S75: =IF(K75="CORREÇÃO NÃO ACEITE",TODAY()-J75,"") | T75: =IF(K75="A VERIFICAR",TODAY()-J75,"")
A76: 45561 | B76: AD | C76: B | D76: -1 | E76: a | F76: 5 | G76: Acabamento entre rodapés | H76: AR | K76: REPARADO | L76: 45377 | N76: 45397 | P76: =IF(K76="NÃO INTERVENCIONADO",TODAY()-J76,"") | Q76: =IF(K76="ENCOMENDADO",TODAY()-J76,"") | R76: =IF(K76="EM OBRA",TODAY()-J76,"") | S76: =IF(K76="CORREÇÃO NÃO ACEITE",TODAY()-J76,"") | T76: =IF(K76="A VERIFICAR",TODAY()-J76,"")
A77: 45561 | B77: AD | C77: B | D77: -1 | E77: a | F77: 6 | G77: Manchas brancas nas laterais das gavetas | H77: AR | K77: REPARADO | L77: 45377 | N77: 45610 | O77: Proprietario enviou email 14/11 10:58 a dizer que não há mais correções a fazer no apto | P77: =IF(K77="NÃO INTERVENCIONADO",TODAY()-J77,"") | Q77: =IF(K77="ENCOMENDADO",TODAY()-J77,"") | R77: =IF(K77="EM OBRA",TODAY()-J77,"") | S77: =IF(K77="CORREÇÃO NÃO ACEITE",TODAY()-J77,"") | T77: =IF(K77="A VERIFICAR",TODAY()-J77,"")
A78: 45561 | B78: AD | C78: B | D78: -1 | E78: a | F78: 7 | G78: Afinar portas (Alinhar com guarnição) | H78: Globaldis | K78: REPARADO | L78: 45377 | N78: 45527 | P78: =IF(K78="NÃO INTERVENCIONADO",TODAY()-J78,"") | Q78: =IF(K78="ENCOMENDADO",TODAY()-J78,"") | R78: =IF(K78="EM OBRA",TODAY()-J78,"") | S78: =IF(K78="CORREÇÃO NÃO ACEITE",TODAY()-J78,"") | T78: =IF(K78="A VERIFICAR",TODAY()-J78,"")
A79: 45561 | B79: AD | C79: B | D79: -1 | E79: a | F79: 8 | G79: Manchas na porta | H79: AR | K79: REPARADO | L79: 45377 | N79: 45397 | P79: =IF(K79="NÃO INTERVENCIONADO",TODAY()-J79,"") | Q79: =IF(K79="ENCOMENDADO",TODAY()-J79,"") | R79: =IF(K79="EM OBRA",TODAY()-J79,"") | S79: =IF(K79="CORREÇÃO NÃO ACEITE",TODAY()-J79,"") | T79: =IF(K79="A VERIFICAR",TODAY()-J79,"")
A80: 45561 | B80: AD | C80: B | D80: -1 | E80: a | F80: 9 | G80: Borracha da porta solta | H80: AR | K80: REPARADO | L80: 45377 | N80: 45397 | P80: =IF(K80="NÃO INTERVENCIONADO",TODAY()-J80,"") | Q80: =IF(K80="ENCOMENDADO",TODAY()-J80,"") | R80: =IF(K80="EM OBRA",TODAY()-J80,"") | S80: =IF(K80="CORREÇÃO NÃO ACEITE",TODAY()-J80,"") | T80: =IF(K80="A VERIFICAR",TODAY()-J80,"")
A81: 45561 | B81: AD | C81: B | D81: -1 | E81: a | F81: 10 | G81: Pedra riscada - falta polir | H81: Pardal | K81: REPARADO | L81: 45377 | N81: 45656 | P81: =IF(K81="NÃO INTERVENCIONADO",TODAY()-J81,"") | Q81: =IF(K81="ENCOMENDADO",TODAY()-J81,"") | R81: =IF(K81="EM OBRA",TODAY()-J81,"") | S81: =IF(K81="CORREÇÃO NÃO ACEITE",TODAY()-J81,"") | T81: =IF(K81="A VERIFICAR",TODAY()-J81,"")
A82: 45561 | B82: AD | C82: B | D82: -1 | E82: a | F82: 11 | G82: Porta danificada - substituir | H82: Globaldis | K82: REPARADO | L82: 45377 | N82: 45397 | P82: =IF(K82="NÃO INTERVENCIONADO",TODAY()-J82,"") | Q82: =IF(K82="ENCOMENDADO",TODAY()-J82,"") | R82: =IF(K82="EM OBRA",TODAY()-J82,"") | S82: =IF(K82="CORREÇÃO NÃO ACEITE",TODAY()-J82,"") | T82: =IF(K82="A VERIFICAR",TODAY()-J82,"")
A83: 45561 | B83: AD | C83: B | D83: -1 | E83: a | F83: 12 | G83: Pontinhos pretos na moldura da porta | H83: AR | K83: REPARADO | L83: 45377 | N83: 45397 | P83: =IF(K83="NÃO INTERVENCIONADO",TODAY()-J83,"") | Q83: =IF(K83="ENCOMENDADO",TODAY()-J83,"") | R83: =IF(K83="EM OBRA",TODAY()-J83,"") | S83: =IF(K83="CORREÇÃO NÃO ACEITE",TODAY()-J83,"") | T83: =IF(K83="A VERIFICAR",TODAY()-J83,"")
A84: 45561 | B84: AD | C84: B | D84: -1 | E84: a | F84: 13 | G84: Limpeza de restos de silicone na bancada | H84: AR | K84: REPARADO | L84: 45377 | N84: 45397 | P84: =IF(K84="NÃO INTERVENCIONADO",TODAY()-J84,"") | Q84: =IF(K84="ENCOMENDADO",TODAY()-J84,"") | R84: =IF(K84="EM OBRA",TODAY()-J84,"") | S84: =IF(K84="CORREÇÃO NÃO ACEITE",TODAY()-J84,"") | T84: =IF(K84="A VERIFICAR",TODAY()-J84,"")
A85: 45561 | B85: AD | C85: B | D85: -1 | E85: a | F85: 14 | G85: Porta danificada - substituida | H85: Globaldis | K85: REPARADO | L85: 45377 | N85: 45397 | P85: =IF(K85="NÃO INTERVENCIONADO",TODAY()-J85,"") | Q85: =IF(K85="ENCOMENDADO",TODAY()-J85,"") | R85: =IF(K85="EM OBRA",TODAY()-J85,"") | S85: =IF(K85="CORREÇÃO NÃO ACEITE",TODAY()-J85,"") | T85: =IF(K85="A VERIFICAR",TODAY()-J85,"")
A86: 45561 | B86: AD | C86: B | D86: -1 | E86: a | F86: 15 | G86: Parede fissurada | H86: AR | K86: REPARADO | L86: 45377 | N86: 45397 | P86: =IF(K86="NÃO INTERVENCIONADO",TODAY()-J86,"") | Q86: =IF(K86="ENCOMENDADO",TODAY()-J86,"") | R86: =IF(K86="EM OBRA",TODAY()-J86,"") | S86: =IF(K86="CORREÇÃO NÃO ACEITE",TODAY()-J86,"") | T86: =IF(K86="A VERIFICAR",TODAY()-J86,"")
A87: 45561 | B87: AD | C87: B | D87: -1 | E87: a | F87: 16 | G87: Disfarçar pregos visíveis na porta | H87: AR | K87: REPARADO | L87: 45377 | N87: 45397 | P87: =IF(K87="NÃO INTERVENCIONADO",TODAY()-J87,"") | Q87: =IF(K87="ENCOMENDADO",TODAY()-J87,"") | R87: =IF(K87="EM OBRA",TODAY()-J87,"") | S87: =IF(K87="CORREÇÃO NÃO ACEITE",TODAY()-J87,"") | T87: =IF(K87="A VERIFICAR",TODAY()-J87,"")
A88: 45561 | B88: AD | C88: B | D88: -1 | E88: a | F88: 17 | G88: Limpeza da tampa da caixa de estores | H88: AR | K88: REPARADO | L88: 45377 | N88: 45397 | P88: =IF(K88="NÃO INTERVENCIONADO",TODAY()-J88,"") | Q88: =IF(K88="ENCOMENDADO",TODAY()-J88,"") | R88: =IF(K88="EM OBRA",TODAY()-J88,"") | S88: =IF(K88="CORREÇÃO NÃO ACEITE",TODAY()-J88,"") | T88: =IF(K88="A VERIFICAR",TODAY()-J88,"")
A89: 45561 | B89: AD | C89: B | D89: -1 | E89: a | F89: 18 | G89: Mancha ao redor dos interruptores | H89: AR | K89: REPARADO | L89: 45377 | N89: 45397 | P89: =IF(K89="NÃO INTERVENCIONADO",TODAY()-J89,"") | Q89: =IF(K89="ENCOMENDADO",TODAY()-J89,"") | R89: =IF(K89="EM OBRA",TODAY()-J89,"") | S89: =IF(K89="CORREÇÃO NÃO ACEITE",TODAY()-J89,"") | T89: =IF(K89="A VERIFICAR",TODAY()-J89,"")
... A97: 45561 | B97: AD | C97: B | D97: -1 | E97: a | F97: 26 | G97: Painel da porta danificado | H97: AR | K97: REPARADO | L97: 45377 | N97: 45397 | P97: =IF(K97="NÃO INTERVENCIONADO",TODAY()-J97,"") | Q97: =IF(K97="ENCOMENDADO",TODAY()-J97,"") | R97: =IF(K97="EM OBRA",TODAY()-J97,"") | S97: =IF(K97="CORREÇÃO NÃO ACEITE",TODAY()-J97,"") | T97: =IF(K97="A VERIFICAR",TODAY()-J97,"")
A98: 45561 | B98: AD | C98: B | D98: -1 | E98: a | F98: 27 | G98: puxar caixilho para dentro | H98: Serrialu | J98: 45747 | K98: REPARADO | L98: 45377 | N98: 45758
A99: 45561 | B99: AD | C99: B | D99: -1 | E99: a | F99: 28 | G99: Caldeira eletrica com uma peça solta | H99: Climacer | J99: 45748 | K99: REPARADO | L99: 45377 | N99: 45782 | O99: JÁ TINHAMOS IDO AO APARTAMENTO COM A REPARAÇÃO EM 07/04
A100: 45561 | B100: AD | C100: B | D100: -1 | E100: a | F100: 29 | G100: O interruptor da cozinha | H100: IEOL | J100: 45747 | K100: REPARADO | L100: 45377 | N100: 45783
A101: 45561 | B101: AD | C101: B | D101: -1 | E101: a | F101: 30 | G101: Um problema com o interruptor da casa de banho. A menos que o liguemos com muita força, a luz não acende. Suspeitamos de algum tipo de mau contacto ou avaria. | H101: IEOL | J101: 45839 | K101: REPARADO | L101: 45377 | N101: 45853
A102: 45561 | B102: AD | C102: B | D102: -1 | E102: a | F102: 31 | G102: A temperatura da água no nosso chuveiro não se mantém quente durante muito tempo. Às vezes basta um duche um pouco mais longo que a água começa logo a ficar fria. Se tomarmos dois duches rápidos seguidos é quase certeiro que a segunda pessoa vai ter de usar água fria. // Agendar com a Climacer, pois a bomba de calor aparenta defeito, não mantendo a temperatua, situação constatada pela Luzimeca, juntamente com o nosso colaborador. | H102: Climacer | J102: 46055 | K102: REPARADO | L102: 45377 | N102: 46170 | O102: Sem anomalia identidficada
A103: 45561 | B103: AD | C103: B | D103: -1 | E103: a | F103: 32 | G103: Já aconteceu diversas vezes o quadro ir a baixo, sem haver razão aparente. Nas últimas vezes nem estávamos a usar um grande volume de eletricidade quando aconteceu. É de notar também que o interruptor do quadro nunca ficou para baixo após cada falha. | H103: IEOL | J103: 46055 | K103: PROCESSO TERMINADO | N103: 46098 | O103: Feedback IEOL: Estivemos lá e fizemos reapertos no quadro e medições e não foi detetado nenhuma anomalia. Orientamos que o morador, caso queira, pode solicitar um aumento da potência.
A104: 45750 | B104: AE | C104: B | D104: 0 | E104: a | F104: 1 | G104: Ligação de bomba de calor | H104: Luzimeca | J104: 45645 | K104: REPARADO | L104: S/ DATA VISTORIA | N104: 45645 | P104: =IF(K103="NÃO INTERVENCIONADO",TODAY()-J104,"") | Q104: =IF(K103="ENCOMENDADO",TODAY()-J104,"") | R104: =IF(K103="EM OBRA",TODAY()-J104,"") | S104: =IF(K103="CORREÇÃO NÃO ACEITE",TODAY()-J104,"") | T104: =IF(K103="A VERIFICAR",TODAY()-J104,"")
A105: 45750 | B105: AE | C105: B | D105: 0 | E105: a | F105: 2 | G105: Trocar peça | H105: Silvas | J105: 45663 | K105: REPARADO | L105: S/ DATA VISTORIA | N105: 45699
A106: 45750 | B106: AE | C106: B | D106: 0 | E106: a | F106: 2 | G106: URGENTE - Intercomunicador não está a ligar para o apartamento correcto e sim para o vizinho // CONTACTO DIRETAMENTE COM A MEO INF. PASSADA PELA IEOL 02/05 - DAQUI 02 SEMANAS ENTRAR EM CONTACTO | H106: IEOL | J106: 45754 | K106: REPARADO | L106: S/ DATA VISTORIA | N106: 45782 | O106: A IEOL informou a MEO sobre o caso e foi-nos fornecido um e-mail para que os proprietários reportem a anomalia. O referido contacto já foi encaminhado aos proprietários. Processo concluído.
A107: 45750 | B107: AE | C107: B | D107: 0 | E107: a | F107: 3 | G107: Afinação da janela | H107: AR | J107: 45735 | K107: REPARADO | L107: S/ DATA VISTORIA | N107: 45741
A108: 45750 | B108: AE | C108: B | D108: 0 | E108: a | F108: 4 | G108: Trocar réguas do pavimento que está inchada. (Indicação do Enc. Bruno Florindo) | H108: Silvas | J108: 45860 | K108: REPARADO | L108: S/ DATA VISTORIA | N108: 45873
A109: 45646 | B109: AF | C109: B | D109: 0 | E109: b | F109: 1 | G109: Racha na parede junto a dispositivo alarme | H109: AR | K109: REPARADO | L109: 45371 | N109: 45523 | P109: =IF(K109="NÃO INTERVENCIONADO",TODAY()-L109,"") | Q109: =IF(K109="ENCOMENDADO",TODAY()-J109,"") | R109: =IF(K109="EM OBRA",TODAY()-J109,"") | S109: =IF(K109="CORREÇÃO NÃO ACEITE",TODAY()-J109,"") | T109: =IF(K109="A VERIFICAR",TODAY()-J109,"")
...

Sheet Resumo - Lote 1
A1: 06/08 a 13/08
A2: Total de apartamentos com vistoria | B2: Anomalias reparadas | C2: Apartamentos reparados | D2: Anomalias por reparar | E2: Apartamentos com anomalias
A3: 142 | B3: 81 | C3: 13 | D3: 964 | E3: 128
A4: 14/08 a 20/08
A5: Total de apartamentos com vistoria | B5: Anomalias reparadas | C5: Apartamentos reparados | D5: Anomalias por reparar | E5: Apartamentos com anomalias | F5: Apartamentos com novas anomalias | G5: Novas anomalias | H5: Apartamentos de novas vistorias com anomalias | I5: Anomalias das novas vistorias
A6: 153 | B6: 298 | C6: 18 | D6: 932 | E6: 133 | F6: 12 | G6: 38 | H6: 11 | I6: 228
A7: 21/08 a 27/08
A8: Total de apartamentos com vistoria | B8: Anomalias reparadas | C8: Apartamentos reparados | D8: Anomalias por reparar | E8: Apartamentos com anomalias | F8: Apartamentos com novas anomalias | G8: Novas anomalias | H8: Apartamentos de novas vistorias com anomalias | I8: Anomalias das novas vistorias | J8: Apartamentos concluídos
A9: 153 | B9: 147 | C9: 38 | D9: 902 | E9: =+A9-J9 -> 127 | F9: =21-H9 -> 20 | G9: =117-I9 -> 88 | H9: 1 | I9: 29 | J9: 26
A10: 28/08 a 03/09
A11: Total de apartamentos com vistoria | B11: Anomalias reparadas | C11: Apartamentos reparados | D11: Anomalias por reparar | E11: Apartamentos com anomalias | F11: Apartamentos com novas anomalias | G11: Novas anomalias | H11: Apartamentos de novas vistorias com anomalias | I11: Anomalias das novas vistorias | J11: Apartamentos concluídos
A12: 153 | B12: 63 | C12: 29 | D12: 983 | E12: 132 | F12: 13 | G12: 144 | H12: 0 | I12: 0 | J12: 21
A13: 04/09 a 10/09
A14: Total de apartamentos com vistoria | B14: Anomalias reparadas | C14: Apartamentos reparados | D14: Anomalias por reparar | E14: Apartamentos com anomalias | F14: Apartamentos com novas anomalias | G14: Novas anomalias | H14: Apartamentos de novas vistorias com anomalias | I14: Anomalias das novas vistorias | J14: Apartamentos concluídos
A15: 153 | B15: 134 | C15: 31 | D15: 874 | E15: 125 | F15: 3 | G15: 25 | H15: 0 | I15: 0 | J15: 28
A16: 11/09 a 17/09
A17: Total de apartamentos com vistoria | B17: Anomalias reparadas | C17: Apartamentos reparados | D17: Anomalias por reparar | E17: Apartamentos com anomalias | F17: Apartamentos com novas anomalias | G17: Novas anomalias | H17: Apartamentos de novas vistorias com anomalias | I17: Anomalias das novas vistorias | J17: Apartamentos concluídos
A18: 153 | B18: 63 | C18: 13 | D18: 839 | E18: 125 | F18: 9 | G18: 28 | H18: 0 | I18: 0 | J18: 28
A19: 18/09 a 24/09
A20: Total de apartamentos com vistoria | B20: Anomalias reparadas | C20: Apartamentos reparados | D20: Anomalias por reparar | E20: Apartamentos com anomalias | F20: Apartamentos com novas anomalias | G20: Novas anomalias | H20: Apartamentos de novas vistorias com anomalias | I20: Anomalias das novas vistorias | J20: Apartamentos concluídos
A21: 153 | B21: 60 | C21: 16 | D21: 817 | E21: 118 | F21: 17 | G21: 38 | H21: 0 | I21: 0 | J21: 28
A22: 25/09 a 01/10
A23: Total de apartamentos com vistoria | B23: Anomalias reparadas | C23: Apartamentos reparados | D23: Anomalias por reparar | E23: Apartamentos com anomalias | F23: Apartamentos com novas anomalias | G23: Novas anomalias | H23: Apartamentos de novas vistorias com anomalias | I23: Anomalias das novas vistorias | J23: Apartamentos concluídos
A24: 156 | B24: 64 | C24: 31 | D24: 847 | E24: 123 | F24: 15 | G24: 48 | H24: 3 | I24: =41+5 -> 46 | J24: 33
A25: 02/10 a 08/10
A26: Total de apartamentos com vistoria | B26: Anomalias reparadas | C26: Apartamentos reparados | D26: Anomalias por reparar | E26: Apartamentos com anomalias | F26: Apartamentos com novas anomalias | G26: Novas anomalias | H26: Apartamentos de novas vistorias com anomalias | I26: Anomalias das novas vistorias | J26: Apartamentos concluídos
A27: 157 | B27: 101 | C27: 22 | D27: =874-8 -> 866 | E27: 125 | F27: 22 | G27: =120-18 -> 102 | H27: 1 | I27: 18 | J27: 27
A28: 09/10 a 15/10
A29: Total de apartamentos com vistoria | B29: Anomalias reparadas | C29: Apartamentos reparados | D29: Anomalias por reparar | E29: Apartamentos com anomalias | F29: Apartamentos com novas anomalias | G29: Novas anomalias | H29: Apartamentos de novas vistorias com anomalias | I29: Anomalias das novas vistorias | J29: Apartamentos concluídos
A30: 158 | B30: 113 | C30: 27 | D30: =854+45 -> 899 | E30: =131 -> 131 | F30: 31 | G30: 103 | H30: 1 | I30: 45 | J30: 26
A31: 16/10 a 22/10
A32: Total de apartamentos com vistoria | B32: Anomalias reparadas | C32: Apartamentos reparados | D32: Anomalias por reparar | E32: Apartamentos com anomalias | F32: Apartamentos com novas anomalias | G32: Novas anomalias | H32: Apartamentos de novas vistorias com anomalias | I32: Anomalias das novas vistorias | J32: Apartamentos concluídos
A33: 158 | B33: 270 | C33: 36 | D33: =773-8 -> 765 | E33: 123 | F33: 38 | G33: 136 | H33: 0 | I33: 0 | J33: 21
A34: 23/10 a 29/10
A35: Total de apartamentos com vistoria | B35: Anomalias reparadas | C35: Apartamentos reparados | D35: Anomalias por reparar | E35: Apartamentos com anomalias | F35: Apartamentos com novas anomalias | G35: Novas anomalias | H35: Apartamentos de novas vistorias com anomalias | I35: Anomalias das novas vistorias | J35: Apartamentos concluídos
A36: 162 | B36: 147 | C36: 41 | D36: =740+3 -> 743 | E36: 134 | F36: 36 | G36: 125 | H36: 4 | I36: =43-7 -> 36 | J36: 20
A37: 30/10 a 05/11
A38: Total de apartamentos com vistoria | B38: Anomalias reparadas | C38: Apartamentos reparados | D38: Anomalias por reparar | E38: Apartamentos com anomalias | F38: Apartamentos com novas anomalias | G38: Novas anomalias | H38: Apartamentos de novas vistorias com anomalias | I38: Anomalias das novas vistorias | J38: Apartamentos concluídos
A39: 162 | B39: 110 | C39: 33 | D39: 690 | E39: 132 | F39: 18 | G39: 57 | H39: 0 | I39: 0 | J39: 19
A40: 06/11 a 12/11
A41: Total de apartamentos com vistoria | B41: Anomalias reparadas | C41: Apartamentos reparados | D41: Anomalias por reparar | E41: Apartamentos com anomalias | F41: Apartamentos com novas anomalias | G41: Novas anomalias | H41: Apartamentos de novas vistorias com anomalias | I41: Anomalias das novas vistorias | J41: Apartamentos concluídos
A42: 164 | B42: 120 | C42: 41 | D42: =682-19 -> 663 | E42: =128-2 -> 126 | F42: 36 | G42: =120-19-8 -> 93 | H42: 2 | I42: =19+8 -> 27 | J42: 30
A43: 13/11 a 26/11
A44: Total de apartamentos com vistoria | B44: Anomalias reparadas | C44: Apartamentos reparados | D44: Anomalias por reparar | E44: Apartamentos com anomalias | F44: Apartamentos com novas anomalias | G44: Novas anomalias | H44: Apartamentos de novas vistorias com anomalias | I44: Anomalias das novas vistorias | J44: Apartamentos concluídos
A45: 165 | B45: =+L121 -> 272 | C45: 69 | D45: 523 | E45: 113 | F45: 49 | G45: 132 | H45: 1 | I45: 15 | J45: 49
A46: 27/11 a 03/12
A47: Total de apartamentos com vistoria | B47: Anomalias reparadas | C47: Apartamentos reparados | D47: Anomalias por reparar | E47: Apartamentos com anomalias | F47: Apartamentos com novas anomalias | G47: Novas anomalias | H47: Apartamentos de novas vistorias com anomalias | I47: Anomalias das novas vistorias | J47: Apartamentos concluídos
A48: 169 | B48: =+F129 -> 161 | C48: 22 | D48: 559 | E48: 117 | F48: 28 | G48: 197 | H48: 4 | I48: =108+28 -> 136 | J48: 48
A49: 04/12 a 11/12
A50: Total de apartamentos com vistoria | B50: Anomalias reparadas | C50: Apartamentos reparados | D50: Anomalias por reparar | E50: Apartamentos com anomalias | F50: Apartamentos com novas anomalias | G50: Novas anomalias | H50: Apartamentos de novas vistorias com anomalias | I50: Anomalias das novas vistorias | J50: Apartamentos concluídos
A51: 169 | B51: 137 | C51: 22 | D51: 482 | E51: 118 | F51: 26 | G51: 60 | H51: 0 | I51: 0 | J51: 49
A52: 12/12 A 18/12
A53: Total de apartamentos com vistoria | B53: Anomalias reparadas | C53: Apartamentos reparados | D53: Anomalias por reparar | E53: Apartamentos com anomalias | F53: Apartamentos com novas anomalias | G53: Novas anomalias | H53: Apartamentos de novas vistorias com anomalias | I53: Anomalias das novas vistorias | J53: Apartamentos concluídos
A54: 169 | B54: 180 | C54: 27 | D54: 394 | E54: 118 | F54: 26 | G54: 15 | H54: 0 | I54: 0 | J54: 50
A55: 19/12 A 08/01
A56: Total de apartamentos com vistoria | B56: Anomalias reparadas | C56: Apartamentos reparados | D56: Anomalias por reparar | E56: Apartamentos com anomalias | F56: Apartamentos com novas anomalias | G56: Novas anomalias | H56: Apartamentos de novas vistorias com anomalias | I56: Anomalias das novas vistorias | J56: Apartamentos concluídos
A57: 169 | B57: 122 | C57: 35 | D57: 303 | E57: 105 | F57: 21 | G57: 31 | H57: 0 | I57: 0 | J57: 72
A58: 09/01 A 15/01
A59: Total de apartamentos com vistoria | B59: Anomalias reparadas | C59: Apartamentos reparados | D59: Anomalias por reparar | E59: Apartamentos com anomalias | F59: Apartamentos com novas anomalias | G59: Novas anomalias | H59: Apartamentos de novas vistorias com anomalias | I59: Anomalias das novas vistorias | J59: Apartamentos concluídos
A60: 169 | B60: 52 | C60: 21 | D60: 257 | E60: 100 | F60: 5 | G60: 6 | H60: 0 | I60: 0 | J60: 75
A61: 16/01 A 22/01
A62: Total de apartamentos com vistoria | B62: Anomalias reparadas | C62: Apartamentos reparados | D62: Anomalias por reparar | E62: Apartamentos com anomalias | F62: Apartamentos com novas anomalias | G62: Novas anomalias | H62: Apartamentos de novas vistorias com anomalias | I62: Anomalias das novas vistorias | J62: Apartamentos concluídos
A63: 169 | B63: =+N162 -> 83 | C63: 17 | D63: =+N159 -> 196 | E63: 100 | F63: 7 | G63: =+N157 -> 22 | H63: 0 | I63: 0 | J63: 82
C73: 21/08 - 27/08 | I73: 28/08 - 03/09
C74: A | D74: por repara em 20.08 | F74: =+D6 -> 932 | I74: A | J74: por repara em 27.08 | L74: =D9 -> 902
C75: B | D75: novas anómalias de 21-27.08 | F75: =+G9 -> 88 | I75: B | J75: novas anómalias de 28.8-03.09 | L75: =+G12 -> 144
C76: C | D76: novos vistorias | F76: =+I9 -> 29 | I76: C | J76: novos vistorias 28.08 - 03.09 | L76: =+I12 -> 0
C77: D | D77: reparado de 21-27.08 | F77: =-B9 -> -147 | I77: D | J77: reparado de 28.8-03.09 | L77: =-B12 -> -63
C79: E | E79: A+B+C+(-D) = E | F79: =SUM(F74:F78) -> 902 | I79: E | K79: A+B+C+(-D) = E | L79: =SUM(L74:L78) -> 983
C82: 11/09 - 17/09 | I82: 18/09 - 24/09
C83: A | D83: Anomalias por reparar 10/09 | F83: 874 | I83: A | J83: Anomalias por reparar 17/09 | L83: 839
C84: B | D84: Novas anomalias | F84: 28 | I84: B | J84: Novas anomalias | L84: 38
C85: C | D85: Anomalias por reparar 17/09 | F85: 839 | I85: C | J85: Anomalias por reparar 24/09 | L85: 817
C86: D | D86: Anomalias reparadas | F86: =F83+F84-F85 -> 63 | I86: D | J86: Anomalias reparadas | L86: 60
E87: A+B-C=D | F87: =F83+F84-F85 -> 63 | K87: A+B-C=D | L87: =L83+L84-L85 -> 60
C90: 25/09 - 01/10 | I90: 02/10 - 08/10
C91: A | D91: Anomalias por reparar 18/09 | F91: 817 | I91: A | J91: Anomalias por reparar 25/09 | L91: 847
C92: B | D92: Novas anomalias | F92: 94 | I92: B | J92: Novas anomalias | L92: 120
C93: C | D93: Anomalias por reparar 01/10 | F93: 847 | I93: C | J93: Anomalias por reparar 08/10 | L93: 866
C94: D | D94: Anomalias reparadas | F94: 64 | I94: D | J94: Anomalias reparadas
E95: A+B-C=D | F95: =F91+F92-F93 -> 64 | K95: A+B-C=D | L95: =L91+L92-L93 -> 101
C99: 09/10 a 15/10 | I99: 16/10 a 22/10
C100: A | D100: Anomalias por reparar 8/10 | F100: 866 | I100: A | J100: Anomalias por reparar 15/10 | L100: 899
C101: B | D101: Novas anomalias | F101: 148 | I101: B | J101: Novas anomalias | L101: 136
C102: C | D102: Anomalias por reparar 15/10 | F102: 899 | I102: C | J102: Anomalias por reparar 22/10 | L102: 765
C103: D | D103: Anomalias reparadas | F103: 0 | I103: D | J103: Anomalias reparadas | L103: 0
E104: A+B-C=D | F104: =F100+F101-F102 -> 115 | K104: A+B-C=D | L104: =L100+L101-L102 -> 270
C108: 23/10 a 29/10 | I108: 30/10 a 06/11
C109: A | D109: Anomalias por reparar 22/10 | F109: 765 | I109: A | J109: Anomalias por reparar 29/10 | L109: 743
C110: B | D110: Novas anomalias | F110: 125 | I110: B | J110: Novas anomalias | L110: 57
C111: C | D111: Anomalias por reparar 29/10 | F111: 743 | I111: C | J111: Anomalias por reparar 06/11 | L111: 690
C112: D | D112: Anomalias reparadas | F112: , | I112: D | J112: Anomalias reparadas
E113: A+B-C=D | F113: =F109+F110-F111 -> 147 | K113: A+B-C=D | L113: =L109+L110-L111 -> 110
C116: 06/11 a 12/11 | I116: 13/11 a 26/11
C117: A | D117: Anomalias por reparar 05/11 | F117: 690 | I117: A | J117: Anomalias por reparar 12/11 | L117: 663
C118: B | D118: Novas anomalias | F118: 93 | I118: B | J118: Novas anomalias | L118: 132
C119: C | D119: Anomalias por reparar 12/11 | F119: 663 | I119: C | J119: Anomalias por reparar 26/11 | L119: 523
C120: D | D120: Anomalias reparadas | I120: D | J120: Anomalias reparadas
E121: A+B-C=D | F121: =F117+F118-F119 -> 120 | K121: A+B-C=D | L121: =L117+L118-L119 -> 272
C124: 27/11 a 03/12 | I124: 04/12 a 11/12
...

Sheet Detalhe1
A1: Detalhes do Contagem de ANOMALIAS - EMPRESA: AR, DATA ESCRITURA: S/ DATA AE (+)
A3: DATA ESCRITURA | B3: FRAÇÃO | C3: BLOCO | D3: PISO | E3: APART. | F3: nº | G3: ANOMALIAS | H3: EMPRESA | I3: ESTADO entre 12.02.25 a 18.02.25 | J3: DATA ENTRADA ANOMALIA | K3: ESTADO | L3: DATA DA VISTORIA | M3: AGENDAM. CORREÇÃO_ DATA ENCOMENDA | N3: DATA de CORREÇÃO_BAIXA | O3: NOVAS ANOMALIAS DESDE 19/12/2024?
A4: 45523 | B4: BE | C4: B | D4: 4 | E4: e | F4: 39 | G4: • Correção dos acabamentos (massa/ silicone) na casa de banho social, junto à banheira e restantes loiças • Anomalia no armário da cozinha (mal funcionamento do sistema de "bloqueio" da porta do armário superior por cima do microondas) • Racha na parede da entrada, junto à porta do apartamento | H4: AR | J4: 45694 | K4: NÃO INTERVENCIONADO | L4: 45398 | O4: SIM
A5: 45561 | B5: Y | C5: A | D5: 8 | E5: a | F5: 21 | G5: Pintura do painel interior | H5: AR | J5: 45588 | K5: CORREÇÃO NÃO ACEITE | L5: 45315
A6: 45516 | B6: EL | C6: D | D6: 0 | E6: c | F6: 16 | G6: Porta lavanderia não abre toda-ver solução (por conta da bomba de calor) - Climacer: Informamos que todo os eletrodomésticos se encontravam no local aquando da instalação da Bomba de calor e do seu arranque. Após a nossa visita verificou-se que existiram alterações às nossas tubagens, para um posterior abastecimento de água à máquina de lavar roupa. Desta forma, toda e qualquer alteração será executada pela empresa, que fez essa instalação adicional. | H6: AR | K6: NÃO INTERVENCIONADO | L6: 45436 | M6: 45693
A7: 45516 | B7: BK | C7: B | D7: 5 | E7: d | F7: 23 | G7: problema na cobertura que faz com que entre/pingue bastante água para a nossa varanda, mais precisamente na zona da passagem da cozinha/lavandaria para a varanda. | H7: AR | J7: 45579 | K7: NÃO INTERVENCIONADO | L7: 45504
A8: 45579 | B8: B | C8: A | D8: -1 | E8: b | F8: 26 | G8: reparação da caixa de correio do bloco A (-1 B) pois a correspondência com a chuva fica inundada. Tem do lado de fora um grande orifício que deixa entrar a chuva quando é tocada a vento. | H8: AR | J8: 45694 | K8: A VERIFICAR | L8: 45566 | O8: SIM
A9: S/ DATA AI | B9: AI | C9: B | D9: 1 | E9: d | F9: 4 | G9: Torneira do chuveiro está danificada - Trocar | H9: AR | K9: ENCOMENDADO | L9: 45391
A10: 45485 | B10: CN | C10: C | D10: 2 | E10: c | F10: 65 | G10: Tubos cobre e cablagem de ligação à Unidade Exterior mal acomodados e com isolamento danificado/ressequido | Soleira já encomenda para ocultar tubagem | H10: AR | J10: 45586 | K10: NÃO INTERVENCIONADO | L10: 45467
A11: 45491 | B11: BJ | C11: B | D11: 5 | E11: c | F11: 26 | G11: Varanda - tem um furo de berbequim na caixilharia da varanda (lado direito) | H11: AR | J11: 45638 | K11: A VERIFICAR | L11: 45371

Sheet Detalhe2
A1: Detalhes do Contagem de ANOMALIAS - EMPRESA: AM&G, ESTADO: NÃO INTERVENCIONADO, DATA ESCRITURA: S/ DATA AE (+)
A3: DATA ESCRITURA | B3: FRAÇÃO | C3: BLOCO | D3: PISO | E3: APART. | F3: nº | G3: ANOMALIAS | H3: EMPRESA | I3: ESTADO entre 05.03.25 a 11.03.25 | J3: DATA ENTRADA ANOMALIA | K3: ESTADO | L3: DATA DA VISTORIA | M3: AGENDAM. CORREÇÃO_ DATA ENCOMENDA | N3: DATA de CORREÇÃO_BAIXA | O3: NOVAS ANOMALIAS DESDE 19/12/2024?
A4: 45562 | B4: EX | C4: D | D4: 2 | E4: a | F4: 20 | G4: Máquina de lavar e sobretudo o frigorífico têm de ser nivelados para estarem equidistantes e alinhados com as restantes bancadas | H4: AM&G | I4: Novo | J4: 45722 | K4: NÃO INTERVENCIONADO | L4: 45495 | O4: SIM

Sheet MACROS (não alterar)
A1: =+'Resumo - Lote 1'!A165 -> Total de apartamentos com vistoria Nota: 1UN - PRESCINDIU DA VISTORIA (APARTAMENTO JÁ ESTAVA HABITADO) | B1: =COUNTA(A7:A177) -> 171 | F1: =+'Resumo - Lote 1'!B165 -> Anomalias reparadas na semana em apreço | O1: =+'Resumo - Lote 1'!C165 -> Apartamentos intervencionados na semana em apreço | U1: =+'Resumo - Lote 1'!D165 -> Anomalias por reparar | Z1: =+'Resumo - Lote 1'!E165 -> Apartamentos com anomalias | AE1: =+'Resumo - Lote 1'!F165 -> Apartamentos com novas anomalias na semana em apreço | AJ1: =+'Resumo - Lote 1'!G165 -> Novas anomalias na semana em apreço | AT1: =+'Resumo - Lote 1'!J165 -> Apartamentos concluídos | AV1: =176+N("total de 176 apartamentos")-5+N("5 vistorias por efectuar a 13/7/2025")-COUNTA(AT5:AT39) -> 136 | AW1: =+IF(AV1='Resumo - Lote 1'!J166,"ok", "ALARME") -> ALARME | BA1: MACRO EXEMPLO:
O2: DATA de CORREÇÃO_BAIXA | P2: (Itens múltiplos) | U2: FRAÇÃO | V2: (Tudo) | Z2: ESTADO | AA2: (Itens múltiplos) | AE2: ESTADO | AF2: (Tudo) | AT2: ESTADO | AU2: (Itens múltiplos)
AE3: DATA ENTRADA ANOMALIA | AF3: (Itens múltiplos) | AJ3: DATA ENTRADA ANOMALIA | AK3: (Itens múltiplos) | BA3: Rótulos de Linha | BB3: Contagem de ANOMALIAS | BC3: Soma de nº
A4: DATA DA VISTORIA | B4: (Itens múltiplos) | F4: DATA de CORREÇÃO_BAIXA | G4: (Itens múltiplos) | O4: Rótulos de Linha | P4: Contagem de APART. | U4: Rótulos de Linha | V4: Contagem de ANOMALIAS | Z4: Rótulos de Linha | AT4: Rótulos de Linha | BA4: A VERIFICAR | BB4: 30 | BC4: 884
O5: REPARADO | P5: 25 | U5: NÃO INTERVENCIONADO | V5: 8 | Z5: AY | AE5: Rótulos de Linha | AF5: Contagem de ANOMALIAS | AJ5: Rótulos de Linha | AK5: Contagem de ANOMALIAS | AT5: AC | BA5: CONFORME PROJETO | BB5: 115 | BC5: 2412
A6: Rótulos de Linha | F6: Rótulos de Linha | G6: Contagem de ANOMALIAS | O6: AN | P6: 1 | U6: CORREÇÃO NÃO ACEITA | V6: 9 | Z6: AZ | AE6: AW | AF6: 1 | AJ6: CONFORME PROJETO | AK6: 2 | AT6: AR | BA6: CORREÇÃO NÃO ACEITE | BB6: 1 | BC6: 6
A7: A | F7: REPARADO | G7: 25 | O7: BU | P7: 2 | U7: Total Geral | V7: 17 | Z7: BK | AE7: BH | AF7: 2 | AJ7: PROCESSO TERMINADO | AK7: 2 | AT7: AT | BA7: ENCOMENDADO | BB7: 31 | BC7: 832
A8: AB | F8: Total Geral | G8: 25 | O8: BX | P8: 3 | Z8: BP | AE8: BS | AF8: 1 | AJ8: REPARADO | AK8: 12 | AT8: AV | BA8: NÃO INTERVENCIONADO | BB8: 18 | BC8: 558
A9: AC | O9: DA | P9: 1 | Z9: BR | AE9: BX | AF9: 1 | AJ9: A VERIFICAR | AK9: 2 | AT9: AW | BA9: PROCESSO TERMINADO | BB9: 49 | BC9: 1371
A10: AD | O10: DV | P10: 3 | Z10: BS | AE10: DJ | AF10: 1 | AJ10: FORA DA GARANTIA | AK10: 1 | AT10: AY | BA10: REPARADO | BB10: 4564 | BC10: 86364
A11: AF | O11: DZ | P11: 1 | Z11: BX | AE11: EB | AF11: 4 | AJ11: Total Geral | AK11: 19 | AT11: AZ | BA11: (em branco)
A12: AG | F12: {=+'Resumo - Lote 1'!I163:J163} -> Semana em análise: | G12: 0 | O12: EB | P12: 7 | Z12: DQ | AE12: EN | AF12: 1 | AT12: BA | BA12: Total Geral | BB12: 4808 | BC12: 92427
A13: AH | F13: =+'Resumo - Lote 1'!I164 -> 46204 | G13: =+'Resumo - Lote 1'!J164 -> 46210 | O13: EC | P13: 2 | Z13: EV | AE13: FE | AF13: 1 | AT13: BE
A14: AI | O14: EO | P14: 1 | Z14: FC | AE14: Total Geral | AF14: 12 | AT14: BH
A15: AJ | O15: ER | P15: 1 | Z15: FO | AT15: BI
A16: AK | O16: FM | P16: 1 | Z16: FZ | AT16: BJ
A17: AL | O17: FZ | P17: 1 | Z17: GA | AT17: BK
A18: AM | O18: H | P18: 1 | Z18: Total Geral | AT18: BL
A19: AN | O19: Total Geral | P19: 25 | AT19: BP
A20: AO | AT20: BR
A21: AP | AT21: BS
A22: AQ | AT22: BT
A23: AR | AT23: BW
A24: AS | AT24: BX
A25: AT | AT25: CO
A26: AU | AT26: CQ
A27: AV | AT27: CZ
A28: AW | AT28: DF
A29: AX | AT29: DG
A30: AY | AT30: DO
A31: AZ | AT31: DQ
... A48: BQ | AT48: Total Geral
A49: BS
A50: BT
A51: BU
A52: BV
A53: BW
A54: BY
A55: BZ
A56: C
A57: CA
A58: CB
A59: CD
A60: CE
... A177: Total Geral
